setup.py
twitched/__init__.py
twitched/bot.py
twitched/chat.py
twitched.egg-info/PKG-INFO
twitched.egg-info/SOURCES.txt
twitched.egg-info/dependency_links.txt
twitched.egg-info/top_level.txt