Metadata-Version: 1.1
Name: twitched
Version: 1.0.0
Summary: A Python library for quickly writing Twitch chat applications and custom chat bots.
Home-page: https://github.com/jeffmvr/twitched
Author: Jeff Merver
Author-email: jeff@merver.me
License: UNKNOWN
Keywords: irc,twitch,twitch.tv,twitch chat,twitch irc
Platform: UNKNOWN
Classifier: Development Status :: 4 - Beta
Classifier: Environment :: No Input/Output (Daemon)
Classifier: Intended Audience :: Developers
Classifier: License :: OSI Approved :: MIT License
Classifier: Natural Language :: English
Classifier: Operating System :: POSIX :: Linux
Classifier: Operating System :: MacOS :: MacOS X
Classifier: Operating System :: Microsoft :: Windows
Classifier: Programming Language :: Python
Classifier: Programming Language :: Python :: 2
Classifier: Programming Language :: Python :: 3
Classifier: Topic :: Communications :: Chat
Classifier: Topic :: Games/Entertainment
Classifier: Topic :: Internet
Classifier: Topic :: Software Development
